simplesqlite/__init__.py
simplesqlite/__version__.py
simplesqlite/_column.py
simplesqlite/_common.py
simplesqlite/_func.py
simplesqlite/_sanitizer.py
simplesqlite/_validator.py
simplesqlite/converter.py
simplesqlite/core.py
simplesqlite/error.py
simplesqlite/model.py
simplesqlite/py.typed
simplesqlite/query.py
simplesqlite/sqlquery.py
simplesqlite/_logger/__init__.py
simplesqlite/_logger/_logger.py
simplesqlite/_logger/_null_logger.py
SimpleSQLite-1.5.2.dist-info/LICENSE
SimpleSQLite-1.5.2.dist-info/METADATA
SimpleSQLite-1.5.2.dist-info/WHEEL
SimpleSQLite-1.5.2.dist-info/top_level.txt
SimpleSQLite-1.5.2.dist-info/RECORD
