Metadata-Version: 2.1
Name: SimpleSQLite
Version: 1.5.2
Summary: SimpleSQLite is a Python library to simplify SQLite database operations: table creation, data insertion and get data as other data formats. Simple ORM functionality for SQLite.
Home-page: https://github.com/thombashi/SimpleSQLite
Author: Tsuyoshi Hombashi
Author-email: tsuyoshi.hombashi@gmail.com
License: MIT License
Project-URL: Changlog, https://github.com/thombashi/SimpleSQLite/releases
Project-URL: Documentation, https://SimpleSQLite.rtfd.io/
Project-URL: Source, https://github.com/thombashi/SimpleSQLite
Project-URL: Tracker, https://github.com/thombashi/SimpleSQLite/issues
Keywords: SQLite,CSV,Google Sheets,JSON
Classifier: Development Status :: 5 - Production/Stable
Classifier: Intended Audience :: Developers
Classifier: License :: OSI Approved :: MIT License
Classifier: Operating System :: Microsoft :: Windows
Classifier: Operating System :: POSIX
Classifier: Operating System :: POSIX :: Linux
Classifier: Programming Language :: Python :: 3
Classifier: Programming Language :: Python :: 3.7
Classifier: Programming Language :: Python :: 3.8
Classifier: Programming Language :: Python :: 3.9
Classifier: Programming Language :: Python :: 3.10
Classifier: Programming Language :: Python :: 3.11
Classifier: Programming Language :: Python :: 3.12
Classifier: Programming Language :: Python :: 3 :: Only
Classifier: Programming Language :: Python :: Implementation :: CPython
Classifier: Programming Language :: Python :: Implementation :: PyPy
Classifier: Topic :: Database
Classifier: Topic :: Software Development :: Libraries
Classifier: Topic :: Software Development :: Libraries :: Python Modules
Classifier: Typing :: Typed
Requires-Python: >=3.7
License-File: LICENSE
Requires-Dist: DataProperty <2,>=1.0.1
Requires-Dist: mbstrdecoder <2,>=1.0.0
Requires-Dist: pathvalidate <4,>=2.5.2
Requires-Dist: sqliteschema <3,>=1.4.0
Requires-Dist: tabledata <2,>=1.1.3
Requires-Dist: typepy <2,>=1.2.0
Provides-Extra: docs
Requires-Dist: sphinx-rtd-theme >=1.2.2 ; extra == 'docs'
Requires-Dist: Sphinx >=2.4 ; extra == 'docs'
Provides-Extra: logging
Requires-Dist: loguru <1,>=0.4.1 ; extra == 'logging'
Provides-Extra: test
Requires-Dist: pytablereader >=0.31.3 ; extra == 'test'
Requires-Dist: pytablewriter >=0.50 ; extra == 'test'
Requires-Dist: pytest >=6.0.1 ; extra == 'test'
Requires-Dist: pytest-discord >=0.1.6 ; extra == 'test'
Requires-Dist: pytest-md-report >=0.5 ; extra == 'test'
Requires-Dist: beautifulsoup4 >=4.10 ; extra == 'test'
